colabmount/__init__.py
colabmount/main.py
colabmount-1.1.1.dist-info/LICENSE
colabmount-1.1.1.dist-info/METADATA
colabmount-1.1.1.dist-info/WHEEL
colabmount-1.1.1.dist-info/RECORD
